{
    "settings": {
        "title": "Einstellungen",
        "error_reading_webtop5_configuration": "Fehler beim Lesen der WebTop5-Konfiguration",
        "default_locale": "Standard-Sprachraum",
        "default_timezone": "Standard-Zeitzone",
        "default_toolbar_icons_size": "Standard-Symbolgröße Funktionsleiste",
        "smtp_auth": "SMTP-Authentifiziung",
        "smtp_starttls": "SMTP STARTTLS",
        "public_url": "URL öffentlich",
        "dav_server_url": "URL DAV-Server",
        "settings_updated_ok": "Konfigurationsupdate erfolgreich",
        "settings_updated_error": "Fehlerhafte Aktualisierung der Konfiguration",
        "not_valid_default_locale": "Standard-Sprachraum ungültig",
        "not_valid_default_timezone": "Standard-Zeitzone ungültig",
        "not_valid_default_toolbar_icons_size": "Standard-Symbolgröße ungültig",
        "not_valid_smtp_auth": "SMTP-Authentifizierung ungültig",
        "not_valid_smtp_starttls": "SMTP STARTTLS ungültig",
        "not_valid_public_url": "Ungültige URL öffentlich",
        "not_valid_dav_server_url": "Ungültige URL DAV-Server",
        "small": "Klein",
        "medium": "Mittel",
        "large": "Groß",
        "advanced_mode": "Erweiterte Einstellungen",
        "pbx_provider": "PBX-Provider",
        "nethvoice_webrest_url": "NethVoice-Webrest-URL",
        "not_valid_nethvoice_webrest_url": "Ungültige NethVoice-Webrest-URL oder PBX Provider nicht eingerichtet auf NethVoice",
        "min_memory": "Speicher-Minimum",
        "max_memory": "Speicher-Maximum",
        "not_a_number_min": "Inhalt ist keine Zahl oder größer als Speicher-Maximum",
        "not_a_number_max": "Inhalt ist keine Zahl oder kleiner als Speicher-Minimum",
        "use_virtualhost": "Bitte einen virtuellen Host für WebTop verwenden",
        "virtualhost_certificate": "Wenn Let’s Encrypt-Zertifikate verwendet werden, bitte den Hostnamen unten zum Feld „Domains“ unter „System“ > „Zertifikate“ > „Let’s Encrypt-Zertifikat anfordern“ hinzufügen.",
        "virtual_host_name": "Name des virtuellen Hosts",
        "jitsi_meet_url": "Jitsi Meet URL",
        "not_valid_jitsi_url": "Ungültige Jitsi Meet URL"
    },
    "about": {
        "title": "Über",
        "website": "Webseite",
        "bug_tracker": "Bug-Tracker"
    },
    "validation": {
        "InvalidPublicUrl": "Ungültige URL öffentlich",
        "InvalidDavServerUrl": "Ungültige URL DAV-Server",
        "InvalidNethvoiceWebrestUrl": "Ungültige NethVoice-Webrest-URL oder PBX Provider nicht eingerichtet auf NethVoice",
        "MaxMemoryHighThanMin": "Speicher-Maximum muß größer als Speicher-Minimum sein",
        "invalid_virtualhost": "Ungültiger virtueller Host"
    },
    "logs": {
        "title": "Logs",
        "follow": "Laufend folgen",
        "stop_follow": "Stoppen",
        "start_follow_button": "Laufend folgen",
        "stop_follow_button": "Folgen stoppen",
        "filter_label": "Regexp-Filter"
    },
    "dashboard":{
        "title": "WebTop Übersicht",
        "app": "WenTop",
        "open_app": "Öffne App",
        "active_users": "Aktive Benutzer",
        "error_reading_webtop5_configuration": "Fehler beim Lesen der WebTop5-Konfiguration",
        "webtop_modules_version": "WebTop Modul-Version",
        "webtop_core": "Kern",
        "webtop_mail": "E-mail",
        "webtop_calendar": "Kalender",
        "webtop_contacts": "Kontakte",
        "webtop_vfs": "VFS-Cloud",
        "webtop_tasks": "Aufgaben",
        "webtop_admin_password": "WebTop-Admin-Passwort",
        "warning": "Warnung",
        "change_default_password": "Das Standardpasswort für den Benutzer admin ist 'admin'. Zur Sicherheit bitte so schnell wie möglich ändern !"
    },
    "docs": {
        "DefaultLocale": "Standardgebietsschema für WebTop-Benutzer.",
        "DefaultTimezone": "Standardzeitzone für WebTop-Benutzer.",
        "DefaultToolbarIconsSize": "Größe der Leistensymbole, verfügbare Werte: klein, mittel, groß. Standard ist mittel.",
        "SmtpAuth": "Wenn aktiv, wird die Authentifizierung für SMTP-Versand von Benutzersitzungen aktiviert. Standard: deaktiviert.",
        "SmtpStarttls": "Wenn aktiv, wird STARTTLS-SMTP-Versand aktiviert. Standard: deaktiviert.",
        "PublicUrl": "Öffentliche URL zum Veröffentlichen von Ressourcen für die Cloud. Standard: http://FQDN/webtop.",
        "DavServerUrl": "DAV-Server-URL für die Konfiguration von CalDAV- und CardDAV-Clients. Standard: https://FQDN/webtop-dav/server.php.",
        "PbxProvider": "Name des PBX-Anbieters.",
        "PbxProviderNethvoiceWebrestUrl": "NethVoice-Basis-URL für API-Aufrufe, die verwendet wird, wenn PBX-Anbieter auf nethvoice festgelegt ist.",
        "MinMemory": "Minimaler Arbeitsspeicher der Tomcat-Instanz in MB.",
        "MaxMemory": "Maximaler Arbeitsspeicher der Tomcat-Instanz in MB.",
        "VirtualHost": "<p>Alias ​​für die WebTop-Anwendung und verwandte Dienste. </p><p>Kann verwendet werden, um auf WebTop zuzugreifen und ActiveSync/CalDAV/CardDAV-Clients zu konfigurieren.</p><p>Der virtuelle Host wird in Download-URLs (sofern keine <b>öffentliche URL</b>definiert wurde) und in Kalender-/Adressbuch-URLs (sofern keine <b>DAV-Server-URL</b> definiert wurde).</p>",
        "JitsiUrl": "Konfigurierte URL des <a target=\"_blank\" href=\"https://jitsi.org/jitsi-meet/\">Jitsi-Meet-Servers</a> für Meetings"
    },
    "save": "Speichern",
    "cancel": "Abbrechen",
    "next": "Weiter",
    "prev": "Zurück",
    "of": "von",
    "rows_per_page": "Zeilen pro Seite",
    "search": "Suchen",
    "all": "Alle",
    "warning": "Warnung"
}