{
    "settings": {
        "title": "Ayarlar",
        "mssql_edition": "MSSQL sürümü",
        "not_valid_edition": "Seçilmiş sürüm geçersiz",
        "error_reading_mssql_configuration": "Microsoft SQL Server yapılandırması okunurken sorun çıktı",
        "settings_updated_ok": "Yapılandırma güncellendi",
        "settings_updated_error": "Yapılandırma güncellenirken sorun çıktı",
        "mssql_is_not_running": "MSSQL sunucusu çalışmıyor",
        "check_sql_service": "SQL Server hizmetini denetleyip yeniden başlatın",
        "not_valid_key": "Ürün anahtarı geçersiz",
        "insert_a_key": "Bir ürün anahtarı ekleyin",
        "product_key": "Ürün anahtarı",
        "sa_user_mgmt": "SA kullanıcı yönetimi",
        "sa_password": "SA parolası",
        "change_password": "Parolayı değiştir",
        "change_sa_password": "SA parolasını değiştir",
        "password": "Parola",
        "confirm_password": "Parola onayı",
        "not_valid_password": "Parola SQL Server ölçütlerine uygun değil",
        "password_updated_ok": "Parola güncellendi",
        "not_equal_password": "Parola ve onayı aynı değil",
        "notice": "Bildir",
        "password_must_respect_criteria": "Parola SQL Server ölçütlerine uygun olmalı yoksa güncellenemez. Parola ölçütlerini gözden geçirmek için",
        "here": "buraya bakabilirsiniz",
        "attention": "Dikkat",
        "sql_server_will_be_restarted": "Parola değiştirilirken SQl Server yeniden başlatılacak"
    },
    "databases": {
        "title": "Veritabanları",
        "title_mgmt": "Veritabanı yönetimi",
        "database_name": "Veritabanı adı",
        "database_already_exists": "Veritabanı zaten var",
        "create": "Veritabanı ekle",
        "not_valid_database_name": "Veritabanı adı geçersiz",
        "database_create_ok": "Veritabanı eklendi",
        "create_database": "Yeni boş bir veritabanı ekle",
        "error_reading_mssql_db_details": "Veritabanı ayrıntıları okunurken sorun çıktı",
        "databases_details": "Veritabanı ayrıntıları",
        "terminal_utility": "Uç birim aracı",
        "terminal_utility_desc": "SQLCMD aracını kullanabilmek için komut satırında şu komutu yürütebilirsiniz",
        "sqlcmd_path": "SQLCMD yolu",
        "copy": "Kopyala"
    },
    "about": {
        "title": "Hakkında",
        "website": "Web sitesi",
        "bug_tracker": "Hata izleyici"
    },
    "validation": {
        "NotValidProductKey": "Ürün anahtarı geçersiz",
        "DbAlreadyExists": "Veritabanı zaten var"
    },
    "logs": {
        "title": "Günlükler",
        "follow": "İzle",
        "stop_follow": "Durdur",
        "start_follow_button": "İzle",
        "stop_follow_button": "İzlemeyi bırak",
        "filter_label": "Kurallı ifade süzgeci"
    },
    "dashboard":{
        "title": "Microsoft SQL Server panosu",
        "app": "MSSQL",
        "mssql_version": "SQL Server sürümü",
        "database": "Veritabanı",
        "databases": "Veritabanları",
        "mssql_status": "SQL Server durumu",
        "error_reading_mssql_status": "Microsoft SQL Server durumu okunurken sorun çıktı",
        "unable_to_connect": "SQL Server ile bağlantı kurulamadı",
        "check_sql_or_sa_password": "SQL Server hizmetinin çalışıp çalışmadığını denetleyin. SA parolasını doğru NethServer işlemini kullanmadan değiştirdiyseniz, bu komutu kullanarak doğru parolayı geri yükleyin",
        "command_to_change_pwd": "ya da parolayı başka bir parola ile doğru şekilde değiştirmek için bu komutu kullanın",
        "enabled": "Etkinleştirilmiş",
        "disabled": "Etkisizleştirilmiş",
        "pre_license_terms": "Bu paketi indirmekle şu koşulları kabul etmiş olursunuz",
        "ms_license_terms": "Microsoft lisans koşulları" 
    },
    "docs": {
        "MssqlEdition": "Listeden SQL Server sürümünü seçin ya da bir Ürün Anahtarı yazın.",
        "SaPassword": "System Administrator kullanıcının parolasını yazın. Parola güncellenemez ise SQL Server parola ölçütlerini denetleyin."
    },
    "save": "Kaydet",
    "cancel": "İptal",
    "next": "Sonraki",
    "prev": "Önceki",
    "of": " / ",
    "rows_per_page": "Bir sayfadaki satır sayısı",
    "search": "Arama",
    "all": "Tümü",
    "package_required": "Eksik paketler",
    "package_required_desc": "Bu sayfaya erişmek için aşağıda listelenen zorunlu paketleri kurmanız gerekir",
    "install_package": "Paketi kur",
    "change": "Değiştir"
}