{
    "action": "Ação",
    "list": "List",
    "search": "Procurar",
    "next": "Seguinte",
    "prev": "Anterior",
    "rows_per_page": "Rows per page",
    "all": "Tudo",
    "advanced_mode": "Opções avançadas",
    "unban": {
        "title": "Unban",
        "BannedIP": "Banned IP",
        "unBanIP": "Unban",
        "Fail2ban_is_probably_down": "Fail2ban is probably stopped, please check the logs",
        "ip_unlocked_error": "The IP has not been unbanned",
        "ip_unlocked_ok": "The IP has been unbanned"
    },
    "settings": {
        "title": "Configurações",
        "configuration": "Configuração",
        "status": "Ativar o serviço",
        "IgnoreIP": "IP Whitelist",
        "mail": "Email notifications",
        "notify_to": "Notify to",
        "add_email": "Add an email",
        "MailJailState": "Notify on jail start/stop events",
        "Recidive_Perpetual": "Recidive jail is perpetual",
        "BanLocalNetwork": "Allow bans on the LAN",
        "LogLevel": "Logging Level",
        "LogLevel_INFO": "INFORMAÇÃO",
        "LogLevel_DEBUG": "DEPURAR",
        "LogLevel_NOTICE": "NOTA",
        "LogLevel_WARNING": "AVISO",
        "LogLevel_ERROR": "ERRO",
        "LogLevel_CRITICAL": "CRITICO",
        "MaxRetry": "Número de tentativas",
        "FindTime": "Time span",
        "BanTime": "Ban time",
        "slider_value": "Valor",
        "FindTime_600": "10 minutos",
        "FindTime_900": "15 minutos",
        "FindTime_1800": "30 minutos",
        "FindTime_3600": "1 hora",
        "FindTime_7200": "2 horas",
        "FindTime_86400": "1 dia",
        "FindTime_172800": "2 dias",
        "FindTime_604800": "1 semana",
        "FindTime_1209600": "2 semanas",
        "BanTime_600": "10 minutos",
        "BanTime_900": "15 minutos",
        "BanTime_1800": "30 minutos",
        "BanTime_3600": "1 hora",
        "BanTime_7200": "2 horas",
        "BanTime_86400": "1 dia",
        "BanTime_172800": "2 dias",
        "BanTime_604800": "1 semana",
        "BanTime_1209600": "2 semanas",
        "settings_updated_error": "definições atualizadas com erro",
        "settings_updated_ok": "definições atualizadas"
    },
    "jails":{
        "title": "Jails",
        "configuration": "Configuração",
        "status": "Ativar o serviço",
        "apache_jails": "Apache",
        "ApacheAuth_status": "Apache - Autenticação",
        "ApacheBadbots_status": "Apache Badbots",
        "ApacheBotsearch_status": "Apache Botsearch",
        "ApacheFakegooglebot_status": "Apache Fakegooglebot",
        "ApacheModsecurity_status": "Apache Modsecurity",
        "ApacheNohome_status": "Apache Nohome",
        "ApacheNoscript_status": "Apache Noscript",
        "ApacheOverflows_status": "Apache Overflows",
        "ApacheScan_status": "Apache Scan",
        "ApacheShellshock_status": "Apache Shellshock",
        "communication_jails": "Comunicação",
        "AsteriskAuth_status": "Asterisk - Autenticação",
        "EjabberdAuth_status": "ejabberd - Autenticação",
        "database_jails": "Base de dados",
        "MysqldAuth_status": "Mysqld - Autenticação",
        "email_jails": "E-mail",
        "Dovecot_status": "Dovecot",
        "PostfixRbl_status": "Postfix Rbl",
        "Postfix_status": "Postfix",
        "PostfixSaslAbuse_status": "Postfix Sasl Abuse",
        "Sieve_status": "Sieve - Autenticação",
        "ftp_jails": "FTP",
        "Vsftpd_status": "Vsftpd - Autenticação",
        "nginx_jails":"Nginx",
        "NginxHttpAuth_status": "Nginx Http Auth",
        "NginxBotSearch_status": "Nginx Bot Search",
        "security_jails": "Segurança",
        "HttpdAdmin_status": "Nethgui (httpd-admin)",
        "PamGeneric_status": "PamGeneric",
        "Recidive_status":"Recidive",
        "ssh_jails": "SSH",
        "Sshd_status": "Sshd Auth",
        "SshdDdos_status": "Sshd Ddos",
        "vpn_jails": "VPN",
        "OpenVpnAuth_status": "OpenVpn Auth",
        "webApps_jails": "web applications",
        "Nextcloud_status": "Nextcloud Auth",
        "Owncloud_status": "Owncloud Auth",
        "ApachePhpMyAdmin_status": "PhpMyAdmin Auth",
        "Roundcube_status":"Roundcube Auth",
        "Rspamd_status": "Rspamd Auth",
        "SogoAuth_status": "Sogo Auth",
        "Urbackup_status": "Urbackup Auth",
        "Webtop_status": "Webtop Auth",
        "settings_updated_error": "definições atualizadas com erro",
        "settings_updated_ok": "definições atualizadas"
    },
    "about": {
        "title": "Sobre",
        "website": "Site da Web",
        "bug_tracker": "Rastreador de erros"
    },
    "logs": {
    "title": "Registos",
    "follow": "Seguir",
    "stop_follow": "Parar"
    },
    "dashboard":{
        "title": "Painel de controle",
        "list_active_jails": "List all active jails",
        "number_of_active_jail": "Active jails",
        "number_bans_per_jail": "Statistics of banned IP per jail",
        "empty_piechart_label": "Limpar dados",
        "number_of_enabled_jails": "Enabled jails",
        "number_total_of_bans":"Total number of banned IP",
        "Fail2ban_is_probably_down": "Fail2ban is probably stopped, please check the logs"

    },
    "validation":{
        "validation_failed": "Validação falhou",
        "not_ip_address": "Invalid IPv4 address: it should be something like '10.0.0.1'",
        "not_valid_email_address": "Invalid mail address: it should be something like 'myname@domain.com'",
        "valid_memberOf_enabled, disabled": "Can be enabled or disabled",
        "valid_memberOf_true, false": "Can be true or false",
        "valid_integer": "Must be a positive integer",
        "valid_memberOf_CRITICAL, ERROR, WARNING, NOTICE, INFO, DEBUG": "Must be a member of CRITICAL, ERROR, WARNING, NOTICE, INFO, DEBUG"
    },
    "docs":{
        "fail2ban": "Fail2ban",
        "more_info_about": "Mais informação acerca de",
        "IgnoreIP": "All IP in this list will never be banned by Fail2ban (One IP per line)",
        "MailJailState": "All relative events to the jail (start or stop), will be notified to root and other recipients",
        "FindTime": "When fail2ban starts, the service looks for attackers in the logs for this time interval",
        "LogLevel": "The DEBUG level could generate huge log size and fill your disk space"
    }
}
