{
    "settings": {
        "title": "Einstellungen",
        "configuration":"Konfiguration",
        "status":"SOGo aktivieren",
        "ActiveSync":"Microsoft ActiveSync aktivieren",
        "Dav":"CalDAV und CardDAV aktivieren",
        "MailAuxiliaryUserAccountsEnabled":"Benutzern erlauben, andere IMAP-Konten hinzuzufügen",
        "AdminUsers":"Administratoren",
        "advanced_mode":"Erweiterte Einstellungen",
        "Notifications":"Benachrichtigungen",
        "ACLs":"E-Mail an beteiligte Benutzer eines Kalenders / Adressbuchs senden",
        "Folders":"E-Mail bei der Erstellung eines Kalenders / Adressbuchs senden",
        "Appointment":"E-Mail an Besprechungsteilnehmer senden",
        "Email":"E-Mail-basierten Alarm zu Ereignissen und Aufgaben senden",
        "VirtualHost":"SOGo nur von dieser Domain (FQDN) aus erreichbar machen",
        "webAccess":"SOGo is available from public network",
        "WOWorkersCount":"Anzahl der Mitarbeiter (einer pro verbundenem activesync-Client)",
        "SOGoInternalSyncInterval":"maximale Zeit in Sekunden vor der Überprüfung nach Änderungen",
        "settings_updated_ok": "Die Einstellungen wurden gut aktualisiert",
        "settings_updated_error": "Die Einstellungen wurden nicht gut aktualisiert"
    },
    "about": {
        "title": "Über",
        "website": "Webseite",
        "bug_tracker": "Bug-Tracker"
    },
    "logs": {
      "title": "Logs",
      "follow": "Zum Ende",
      "stop_follow": "Stoppen",
      "start_follow_button": "Zum Ende",
      "stop_follow_button": "Stop folgende",
      "filter_label": "Regexp-Filter"
    },
    "dashboard":{
        "title": "Übersicht"
    },
    "docs":{
      "more_info_about":"Weitere Informationen zu",
      "sogo": "SOGo"
    },
    "validation":{
      "validation_failed": "Die Validierung ist fehlgeschlagen",
      "not_valid_username": "Dies ist kein gültiger Benutzername",
      "valid_hostname_fqdn_1_9223372036854775807": "Dies ist kein gültiger vollqualifizierter vollqualifizierter Domänenname (so etwas wie domain.org)",
      "Bad_Notification_Element": "Dies ist keine gute Benachrichtigungseinstellung."
    }
}
